chess_ant/__init__.py
chess_ant/chess_ant.py
chess_ant/chess_mcts.py
chess_ant-0.1.0.dist-info/LICENSE.txt
chess_ant-0.1.0.dist-info/METADATA
chess_ant-0.1.0.dist-info/WHEEL
chess_ant-0.1.0.dist-info/entry_points.txt
chess_ant-0.1.0.dist-info/top_level.txt
chess_ant-0.1.0.dist-info/RECORD
