Metadata-Version: 2.1
Name: chess-ant
Version: 0.1.0
Summary: Simulator to solve chess problems with MCTS Solver and Genetic Programming.
Home-page: https://github.com/akuroiwa/chess-ant
Author: Akihiro Kuroiwa, ChatGPT of OpenAI
Author-email: akuroiwa@env-reform.com, 
License: GNU/GPLv3+
Keywords: evolutionary algorithms,genetic programming,gp,chess,fen,pgn
Platform: any
Classifier: Development Status :: 3 - Alpha
Classifier: Environment :: Console
Classifier: Intended Audience :: Developers
Classifier: Intended Audience :: Science/Research
Classifier: Intended Audience :: Education
Classifier: Operating System :: OS Independent
Classifier: License :: OSI Approved :: GNU General Public License v3 or later (GPLv3+)
Classifier: Programming Language :: Python :: 3 :: Only
Classifier: Topic :: Scientific/Engineering
Classifier: Topic :: Software Development
Classifier: Topic :: Games/Entertainment :: Board Games
Classifier: Topic :: Software Development :: Libraries :: Python Modules
Requires-Python: >=3.7, !=3.10.*
License-File: LICENSE.txt
Requires-Dist: chess
Requires-Dist: deap
Requires-Dist: mcts
Requires-Dist: mcts-solver
Requires-Dist: pandas
Requires-Dist: scipy
Provides-Extra: classification
Requires-Dist: chess-classification ; extra == 'classification'
Requires-Dist: transformers ; extra == 'classification'
